pysnooperDB
